_internal/__init__.py
_internal/_internal.abi3.so
knowledge_graph/__init__.py
knowledge_graph/__main__.py
knowledge_graph/cli/__init__.py
knowledge_graph/cli/embedding_support.py
knowledge_graph/cli/ingest.py
knowledge_graph/cli/interactive.py
knowledge_graph/cli/parser.py
knowledge_graph/cli/runtime.py
knowledge_graph/component.py
knowledge_graph/config.py
knowledge_graph/embeddings.py
knowledge_graph/extraction.py
knowledge_graph/extractors/__init__.py
knowledge_graph/extractors/base.py
knowledge_graph/extractors/heuristic.py
knowledge_graph/extractors/llm.py
knowledge_graph/llm/__init__.py
knowledge_graph/llm/llm_utils.py
knowledge_graph/llm/prompts.py
knowledge_graph/llm/qa.py
knowledge_graph/llm/semantic.py
knowledge_graph/main.py
knowledge_graph/semantic.py
knowledge_graph/service.py
knowledge_graph/store.py
knowledge_graph/types.py
knowledge_graph/webservice.py
lance_graph/__init__.py
lance_graph-0.5.0.dist-info/METADATA
lance_graph-0.5.0.dist-info/WHEEL
lance_graph-0.5.0.dist-info/entry_points.txt
lance_graph-0.5.0.dist-info/licenses/LICENSE
lance_graph-0.5.0.dist-info/RECORD
