Metadata-Version: 2.4
Name: lance-graph
Version: 0.5.0
Classifier: Development Status :: 3 - Alpha
Classifier: Intended Audience :: Science/Research
Classifier: License :: OSI Approved :: Apache Software License
Classifier: Operating System :: OS Independent
Classifier: Programming Language :: Python
Classifier: Programming Language :: Python :: 3
Classifier: Programming Language :: Python :: 3 :: Only
Classifier: Programming Language :: Python :: 3.9
Classifier: Programming Language :: Python :: 3.10
Classifier: Programming Language :: Python :: 3.11
Classifier: Programming Language :: Python :: 3.12
Classifier: Programming Language :: Rust
Classifier: Topic :: Scientific/Engineering
Requires-Dist: pyarrow>=14
Requires-Dist: pyyaml>=6.0
Requires-Dist: fastapi>=0.104.0
Requires-Dist: uvicorn>=0.24.0
Requires-Dist: pydantic>=2.0.0
Requires-Dist: openai>=1.52.0
Requires-Dist: pylance
Requires-Dist: fsspec
Requires-Dist: gcsfs
Requires-Dist: ruff ; extra == 'dev'
Requires-Dist: pyright ; extra == 'dev'
Requires-Dist: pytest ; extra == 'tests'
Requires-Dist: pyarrow>=14 ; extra == 'tests'
Requires-Dist: pandas ; extra == 'tests'
Requires-Dist: ruff ; extra == 'tests'
Requires-Dist: streamlit>=1.30.0 ; extra == 'ui'
Requires-Dist: streamlit-agraph>=0.0.45 ; extra == 'ui'
Provides-Extra: dev
Provides-Extra: tests
Provides-Extra: ui
License-File: LICENSE
Summary: Python bindings for the lance-graph Cypher engine
Keywords: graph,cypher,lance,arrow
Author-email: Lance Devs <dev@lancedb.com>
Requires-Python: >=3.9
